todopro_cli/__init__.py
todopro_cli/config.py
todopro_cli/main.py
todopro_cli/api/__init__.py
todopro_cli/api/analytics.py
todopro_cli/api/auth.py
todopro_cli/api/client.py
todopro_cli/api/labels.py
todopro_cli/api/projects.py
todopro_cli/api/tasks.py
todopro_cli/commands/__init__.py
todopro_cli/commands/analytics.py
todopro_cli/commands/auth.py
todopro_cli/commands/config.py
todopro_cli/commands/contexts.py
todopro_cli/commands/labels.py
todopro_cli/commands/projects.py
todopro_cli/commands/tasks.py
todopro_cli/commands/timer.py
todopro_cli/commands/utils.py
todopro_cli/models/__init__.py
todopro_cli/models/project.py
todopro_cli/models/task.py
todopro_cli/models/user.py
todopro_cli/ui/__init__.py
todopro_cli/ui/formatters.py
todopro_cli/utils/__init__.py
todopro_cli/utils/background.py
todopro_cli/utils/error_logger.py
todopro_cli/utils/task_helpers.py
todopro_cli/utils/typer_helpers.py
todopro_cli/utils/update_checker.py
todopro_cli-0.1.0.dist-info/METADATA
todopro_cli-0.1.0.dist-info/WHEEL
todopro_cli-0.1.0.dist-info/entry_points.txt
todopro_cli-0.1.0.dist-info/top_level.txt
todopro_cli-0.1.0.dist-info/RECORD
