Metadata-Version: 2.4
Name: todopro-cli
Version: 0.1.0
Summary: A professional command-line interface for TodoPro task management system
Author-email: minhdqdev <minhdq.dev@gmail.com>
Classifier: Development Status :: 3 - Alpha
Classifier: Intended Audience :: Developers
Classifier: Programming Language :: Python :: 3
Classifier: Programming Language :: Python :: 3.12
Requires-Python: >=3.12
Requires-Dist: click<8.2,>=8.1
Requires-Dist: rich>=13.7.0
Requires-Dist: httpx>=0.27.0
Requires-Dist: platformdirs>=4.2.0
Requires-Dist: pydantic[email]>=2.6.0
Requires-Dist: python-dotenv>=1.0.0
Requires-Dist: pyyaml>=6.0.1
Requires-Dist: typer>=0.21.1
Requires-Dist: requests>=2.32.5
Requires-Dist: packaging>=26.0
Provides-Extra: dev
Requires-Dist: pytest>=8.0.0; extra == "dev"
Requires-Dist: pytest-asyncio>=0.23.0; extra == "dev"
Requires-Dist: pytest-cov>=4.1.0; extra == "dev"
Requires-Dist: black>=24.0.0; extra == "dev"
Requires-Dist: ruff>=0.2.0; extra == "dev"
Requires-Dist: mypy>=1.8.0; extra == "dev"
